HelloPypiApacph/__init__.py
HelloPypiApacph/calc.py
HelloPypiApacph/dt.py
HelloPypiApacph-0.3.0.dist-info/LICENSE
HelloPypiApacph-0.3.0.dist-info/METADATA
HelloPypiApacph-0.3.0.dist-info/WHEEL
HelloPypiApacph-0.3.0.dist-info/top_level.txt
HelloPypiApacph-0.3.0.dist-info/RECORD
