Metadata-Version: 2.1
Name: HelloPypiApacph
Version: 0.3.0
Summary: A small example package
Author-email: Po-Hsun Cheng <apacph@gmail.com>
License: MIT License
Project-URL: Homepage, https://gitlab.com/apacph/HelloPypiApacph
Project-URL: Issues, https://gitlab.com/apacph/HelloPypiApacph/issues
Classifier: Programming Language :: Python :: 3
Classifier: License :: OSI Approved :: MIT License
Classifier: Operating System :: OS Independent
Requires-Python: >=3.8
License-File: LICENSE
